README.md
setup.py
yhxmmdk/__init__.py
yhxmmdk/print_str.py
yhxmmdk.egg-info/PKG-INFO
yhxmmdk.egg-info/SOURCES.txt
yhxmmdk.egg-info/dependency_links.txt
yhxmmdk.egg-info/top_level.txt