Metadata-Version: 2.1
Name: yhxmmdk
Version: 0.0.1
Summary: PyPI using demo
Home-page: 
Author: hayang
Author-email: 469358331@qq.com
Classifier: Programming Language :: Python :: 3
Classifier: License :: OSI Approved :: MIT License
Classifier: Operating System :: OS Independent
Requires-Python: >=3.6
